setup.py
nlpsk/__init__.py
nlpsk.egg-info/PKG-INFO
nlpsk.egg-info/SOURCES.txt
nlpsk.egg-info/dependency_links.txt
nlpsk.egg-info/top_level.txt