Metadata-Version: 2.4
Name: nlpsk
Version: 0.1
Summary: NLP toolkit based on scikit-learn
Author: DEV | SJ | Si Jey
Author-email: sijeydev@email.com
Dynamic: author
Dynamic: author-email
Dynamic: summary
